alumathpeer2/__init__.py
alumathpeer2-0.1.0.dist-info/METADATA
alumathpeer2-0.1.0.dist-info/WHEEL
alumathpeer2-0.1.0.dist-info/top_level.txt
alumathpeer2-0.1.0.dist-info/RECORD
