Metadata-Version: 2.4
Name: alumathpeer2
Version: 0.1.0
Summary: A matrix multiplication library
Home-page: https://github.com/mugishasam123/matrixmultiply
Author: Samuel Mugisha
Author-email: m.samuel@alustudent.com
Classifier: Programming Language :: Python :: 3
Classifier: License :: OSI Approved :: MIT License
Classifier: Operating System :: OS Independent
Requires-Python: >=3.6
Dynamic: author
Dynamic: author-email
Dynamic: classifier
Dynamic: description
Dynamic: description-content-type
Dynamic: home-page
Dynamic: requires-python
Dynamic: summary
